Workbook

Sheet Drivers
A1: Alphabet Inc. (GOOGL) — driver inputs
A2: Blue cells are inputs. Everything else in this workbook is a formula. Change a blue cell and the value per share on 'Valuation' moves.
A4: Driver | B4: 2026E | C4: 2027E | D4: 2028E | E4: 2029E | F4: 2030E | G4: 2031E | H4: Note
A5: Google Search & other
A6: queries | B6: 0.065 | C6: 0.055 | D6: 0.05 | E6: 0.045 | F6: 0.04 | G6: 0.035
A7: ad coverage | B7: -0.01 | C7: -0.015 | D7: -0.015 | E7: -0.01 | F7: -0.005 | G7: 0
A8: price per click | B8: 0.13 | C8: 0.08 | D8: 0.062 | E8: 0.05 | F8: 0.045 | G8: 0.04
A9: YouTube ads
A10: watch hours | B10: 0.05 | C10: 0.045 | D10: 0.04 | E10: 0.035 | F10: 0.03 | G10: 0.03
A11: ad load | B11: 0.02 | C11: 0.015 | D11: 0.01 | E11: 0.005 | F11: 0 | G11: 0
A12: cpm | B12: 0.075 | C12: 0.05 | D12: 0.04 | E12: 0.035 | F12: 0.03 | G12: 0.025
A13: Google Network
A14: runoff | B14: -0.03 | C14: -0.04 | D14: -0.04 | E14: -0.05 | F14: -0.05 | G14: -0.05
A15: Subscriptions, platforms & devices
A16: subscribers | B16: 0.14 | C16: 0.12 | D16: 0.1 | E16: 0.09 | F16: 0.08 | G16: 0.07
A17: arpu | B17: 0.03 | C17: 0.03 | D17: 0.025 | E17: 0.025 | F17: 0.02 | G17: 0.02
A18: Google Cloud
A19: capacity | B19: 0.55 | C19: 0.34 | D19: 0.28 | E19: 0.23 | F19: 0.19 | G19: 0.15
A20: Other Bets
A21: growth | B21: 0.1 | C21: 0.15 | D21: 0.2 | E21: 0.2 | F21: 0.2 | G21: 0.2
A23: EBITDA margin (cash margin, pre-D&A) | B23: 0.385 | C23: 0.392 | D23: 0.398 | E23: 0.402 | F23: 0.405 | G23: 0.407 | H23: We forecast this and DERIVE EBIT by subtracting depreciation.
A24: Capex % of revenue | B24: 0.295 | C24: 0.27 | D24: 0.24 | E24: 0.21 | F24: 0.185 | G24: 0.17 | H24: Drives the depreciation schedule.
A25: Tax rate | B25: 0.185 | C25: 0.19 | D25: 0.19 | E25: 0.19 | F25: 0.19 | G25: 0.19
A26: Net working capital % of revenue | B26: 0.02 | C26: 0.02 | D26: 0.02 | E26: 0.02 | F26: 0.02 | G26: 0.02
A28: Base year revenue by segment ($)
A29: Google Search & other | B29: 224532000000
A30: YouTube ads | B30: 40367000000
A31: Google Network | B31: 29792000000
A32: Subscriptions, platforms & devices | B32: 48030000000
A33: Google Cloud | B33: 58705000000
A34: Other Bets | B34: 1537000000
A36: WACC | B36: 0.0875 | H36: Single definition. Every sheet references this cell — there is no override.
A37: Terminal growth | B37: 0.03
A38: Diluted shares | B38: 12309000000
A39: Cash & marketable securities | B39: 242474000000
A40: Equity investments (stakes) | B40: 124259000000
A41: Debt | B41: 100164000000
A42: Operating leases | B42: 18037000000
A43: Spot price | B43: 377.65

Sheet Revenue
A1: Segment revenue build — each line is the product of its drivers
A3: Segment | B3: 2026E | C3: 2027E | D3: 2028E | E3: 2029E | F3: 2030E | G3: 2031E
A4: Google Search & other | B4: =Drivers!$B$29*(1+Drivers!B$6)*(1+Drivers!B$7)*(1+Drivers!B$8) | C4: =B4*(1+Drivers!C$6)*(1+Drivers!C$7)*(1+Drivers!C$8) | D4: =C4*(1+Drivers!D$6)*(1+Drivers!D$7)*(1+Drivers!D$8) | E4: =D4*(1+Drivers!E$6)*(1+Drivers!E$7)*(1+Drivers!E$8) | F4: =E4*(1+Drivers!F$6)*(1+Drivers!F$7)*(1+Drivers!F$8) | G4: =F4*(1+Drivers!G$6)*(1+Drivers!G$7)*(1+Drivers!G$8)
A5: YouTube ads | B5: =Drivers!$B$30*(1+Drivers!B$10)*(1+Drivers!B$11)*(1+Drivers!B$12) | C5: =B5*(1+Drivers!C$10)*(1+Drivers!C$11)*(1+Drivers!C$12) | D5: =C5*(1+Drivers!D$10)*(1+Drivers!D$11)*(1+Drivers!D$12) | E5: =D5*(1+Drivers!E$10)*(1+Drivers!E$11)*(1+Drivers!E$12) | F5: =E5*(1+Drivers!F$10)*(1+Drivers!F$11)*(1+Drivers!F$12) | G5: =F5*(1+Drivers!G$10)*(1+Drivers!G$11)*(1+Drivers!G$12)
A6: Google Network | B6: =Drivers!$B$31*(1+Drivers!B$14) | C6: =B6*(1+Drivers!C$14) | D6: =C6*(1+Drivers!D$14) | E6: =D6*(1+Drivers!E$14) | F6: =E6*(1+Drivers!F$14) | G6: =F6*(1+Drivers!G$14)
A7: Subscriptions, platforms & devices | B7: =Drivers!$B$32*(1+Drivers!B$16)*(1+Drivers!B$17) | C7: =B7*(1+Drivers!C$16)*(1+Drivers!C$17) | D7: =C7*(1+Drivers!D$16)*(1+Drivers!D$17) | E7: =D7*(1+Drivers!E$16)*(1+Drivers!E$17) | F7: =E7*(1+Drivers!F$16)*(1+Drivers!F$17) | G7: =F7*(1+Drivers!G$16)*(1+Drivers!G$17)
A8: Google Cloud | B8: =Drivers!$B$33*(1+Drivers!B$19) | C8: =B8*(1+Drivers!C$19) | D8: =C8*(1+Drivers!D$19) | E8: =D8*(1+Drivers!E$19) | F8: =E8*(1+Drivers!F$19) | G8: =F8*(1+Drivers!G$19)
A9: Other Bets | B9: =Drivers!$B$34*(1+Drivers!B$21) | C9: =B9*(1+Drivers!C$21) | D9: =C9*(1+Drivers!D$21) | E9: =D9*(1+Drivers!E$21) | F9: =E9*(1+Drivers!F$21) | G9: =F9*(1+Drivers!G$21)
A10: Total revenue | B10: =SUM(B4:B9) | C10: =SUM(C4:C9) | D10: =SUM(D4:D9) | E10: =SUM(E4:E9) | F10: =SUM(F4:F9) | G10: =SUM(G4:G9)
A11: Growth | B11: =B10/SUM(Drivers!$B$29:$B$34)-1 | C11: =C10/B10-1 | D11: =D10/C10-1 | E11: =E10/D10-1 | F11: =F10/E10-1 | G11: =G10/F10-1

Sheet Depreciation
A1: Vintage depreciation schedule
A2: Assets split 72% short-lived (6yr) / 28% long-lived (25yr), half-year convention in the vintage year. This is the schedule the consensus feed does not carry.
A4: Item | B4: 2026E | C4: 2027E | D4: 2028E | E4: 2029E | F4: 2030E | G4: 2031E
A5: Capex ($) | B5: =Revenue!B10*Drivers!B$24 | C5: =Revenue!C10*Drivers!C$24 | D5: =Revenue!D10*Drivers!D$24 | E5: =Revenue!E10*Drivers!E$24 | F5: =Revenue!F10*Drivers!F$24 | G5: =Revenue!G10*Drivers!G$24
A6: D&A ($) — modelled | B6: 3.9998266e+10 | C6: 5.6638991e+10 | D6: 7.3081355e+10 | E6: 8.9289549e+10 | F6: 1.0260888e+11 | G6: 1.1106458e+11 | H6: Computed in build/cases.py:depreciation_path from capex vintages.
A7: D&A % of revenue | B7: =B6/Revenue!B10 | C7: =C6/Revenue!C10 | D7: =D6/Revenue!D10 | E7: =E6/Revenue!E10 | F7: =F6/Revenue!F10 | G7: =G6/Revenue!G10
A8: Capex / D&A ratio | B8: =B5/B6 | C8: =C5/C6 | D8: =D5/D6 | E8: =E5/E6 | F8: =F5/F6 | G8: =G5/G6

Sheet Valuation
A1: GOOGL — unlevered FCFF DCF, mid-year convention
A3: Line | B3: 2026E | C3: 2027E | D3: 2028E | E3: 2029E | F3: 2030E | G3: 2031E
A4: Revenue | B4: =Revenue!B10 | C4: =Revenue!C10 | D4: =Revenue!D10 | E4: =Revenue!E10 | F4: =Revenue!F10 | G4: =Revenue!G10
A5: EBITDA margin | B5: =Drivers!B$23 | C5: =Drivers!C$23 | D5: =Drivers!D$23 | E5: =Drivers!E$23 | F5: =Drivers!F$23 | G5: =Drivers!G$23
A6: EBITDA | B6: =B4*B5 | C6: =C4*C5 | D6: =D4*D5 | E6: =E4*E5 | F6: =F4*F5 | G6: =G4*G5
A7: D&A | B7: =Depreciation!B6 | C7: =Depreciation!C6 | D7: =Depreciation!D6 | E7: =Depreciation!E6 | F7: =Depreciation!F6 | G7: =Depreciation!G6
A8: EBIT | B8: =B6-B7 | C8: =C6-C7 | D8: =D6-D7 | E8: =E6-E7 | F8: =F6-F7 | G8: =G6-G7
A9: EBIT margin | B9: =B8/B4 | C9: =C8/C4 | D9: =D8/D4 | E9: =E8/E4 | F9: =F8/F4 | G9: =G8/G4
A10: Tax rate | B10: =Drivers!B$25 | C10: =Drivers!C$25 | D10: =Drivers!D$25 | E10: =Drivers!E$25 | F10: =Drivers!F$25 | G10: =Drivers!G$25
A11: NOPAT | B11: =B8*(1-B10) | C11: =C8*(1-C10) | D11: =D8*(1-D10) | E11: =E8*(1-E10) | F11: =F8*(1-F10) | G11: =G8*(1-G10)
A12: Capex | B12: =Depreciation!B5 | C12: =Depreciation!C5 | D12: =Depreciation!D5 | E12: =Depreciation!E5 | F12: =Depreciation!F5 | G12: =Depreciation!G5
A13: NWC | B13: =B4*Drivers!B$26 | C13: =C4*Drivers!C$26 | D13: =D4*Drivers!D$26 | E13: =E4*Drivers!E$26 | F13: =F4*Drivers!F$26 | G13: =G4*Drivers!G$26
A14: Change in NWC | B14: =B13-SUM(Drivers!$B$29:$B$34)*Drivers!$B$26 | C14: =C13-B13 | D14: =D13-C13 | E14: =E13-D13 | F14: =F13-E13 | G14: =G13-F13
A15: FCFF | B15: =B11+B7-B12-B14 | C15: =C11+C7-C12-C14 | D15: =D11+D7-D12-D14 | E15: =E11+E7-E12-E14 | F15: =F11+F7-F12-F14 | G15: =G11+G7-G12-G14
A16: Discount factor | B16: =1/(1+Drivers!$B$36)^(0+0.5) | C16: =1/(1+Drivers!$B$36)^(1+0.5) | D16: =1/(1+Drivers!$B$36)^(2+0.5) | E16: =1/(1+Drivers!$B$36)^(3+0.5) | F16: =1/(1+Drivers!$B$36)^(4+0.5) | G16: =1/(1+Drivers!$B$36)^(5+0.5)
A17: PV of FCFF | B17: =B15*B16 | C17: =C15*C16 | D17: =D15*D16 | E17: =E15*E16 | F17: =F15*F16 | G17: =G15*G16
A19: PV of explicit forecast | B19: =SUM(B17:G17)
A20: Terminal value | B20: =G15*(1+Drivers!$B$37)/(Drivers!$B$36-Drivers!$B$37)
A21: PV of terminal value | B21: =B20/(1+Drivers!$B$36)^(6-0.5)
A22: Enterprise value | B22: =B19+B21
A23: + Cash & marketable securities | B23: =Drivers!$B$39
A24: + Equity investments | B24: =Drivers!$B$40
A25: - Debt | B25: =-Drivers!$B$41
A26: - Operating leases | B26: =-Drivers!$B$42
A27: Equity value | B27: =B22+B23+B24+B25+B26
A28: Value per share | B28: =B27/Drivers!$B$38
A29: Spot price | B29: =Drivers!$B$43
A30: Upside / (downside) | B30: =B28/B29-1
A31: Terminal value % of EV | B31: =B21/B22
A33: Sanity check: WACC minus terminal growth should exceed 150bp.
A34: WACC - g | B34: =Drivers!$B$36-Drivers!$B$37 | C34: =IF(B34>0.015,"OK","FAIL — terminal value unstable")

Sheet Variant
A1: Our forecast against the analyst distribution
A2: Street figures are the consensus feed as retrieved 2026-08-05. Low/high are the support of published estimates, not a confidence interval.
A4: Fiscal year | B4: Our revenue | C4: Street avg | D4: Street low | E4: Street high | F4: Delta % | G4: Analysts | H4: In range?
A5: 2026 | B5: 4.9196496e+11 | C5: 495194912007 | D5: 488834946807 | E5: 500626666069 | F5: -0.0065225926 | G5: 35 | H5: yes
A6: 2027 | B6: 5.6866639e+11 | C6: 605866802904 | D6: 574063447987 | E6: 653723173062 | F6: -0.061400321 | G6: 39 | H6: OUTSIDE
A7: 2028 | B7: 6.4469924e+11 | C7: 721625171799 | D7: 539933823678 | E7: 798798263142 | F7: -0.10660095 | G7: 38 | H7: yes
A8: 2029 | B8: 7.2111277e+11 | C8: 815730364847 | D8: 714927001762 | E8: 879702248650 | F8: -0.11599126 | G8: 29 | H8: yes
A9: 2030 | B9: 7.9806188e+11 | C9: 936258242857 | D9: 820560723599 | E9: 1009682263958 | F9: -0.14760496 | G9: 35 | H9: OUTSIDE

Sheet Decision
A1: GOOGL — scenarios, expected value and sizing
A3: Case | B3: Value / share | C3: Probability | D3: vs spot | E3: Anchor
A4: Bear | B4: 114.72668 | C4: 0.25 | D4: =B4/Valuation!B29-1 | E4: consensus dispersion
A5: Base | B5: 195.65033 | C5: 0.45 | D5: =B5/Valuation!B29-1 | E5: judgment
A6: Bull | B6: 439.30875 | C6: 0.3 | D6: =B6/Valuation!B29-1 | E6: consensus dispersion
A7: Expected value | B7: =SUMPRODUCT(B4:B6,C4:C6) | C7: =SUM(C4:C6) | D7: =B7/Valuation!B29-1
A9: Rating | B9: SHORT
A10: Risk / reward | B10: 2.0943186 | E10: short framing
A11: Payoff ratio b | B11: 2.0943186 | E11: reward / risk
A12: p(win) | B12: 0.7 | E12: probability mass favouring the position
A13: Kelly f | B13: 0.55675532
A14: Quarter-Kelly | B14: 0.13918883 | E14: 0.25 x Kelly
A15: Liquidity cap | B15: 22.4 | E15: 20% of ADV over 5 days
A16: Risk-budget cap | B16: 0.091872613 | E16: 1.5% of NAV at risk
A17: Concentration cap | B17: 0.05 | E17: single-name hard limit
A18: Position size | B18: 0.05 | E18: binding: concentration cap
A20: Basis: illustrative $1bn book. Illustrative only.

Sheet Notes
A1: Sources, method and limitations
A3: Base year: trailing twelve months to 2026-06-30, all statement inputs from SEC XBRL companyconcept (CIK 0001652044).
A4: Quarterly series are reconstructed from filed facts: Q4 is derived as fiscal year minus the nine-month cumulative, and cash-flow items are unwound from year-to-date cumulatives.
A5: Consensus estimates and price targets: FMP analyst/financial-estimates and analyst/price-target-consensus, retrieved 2026-08-05.
A6: Segment revenue: FMP statements/revenue-product-segmentation. No SEC fallback exists because companyfacts flattens dimensioned facts; the segment sum is reconciled to consolidated revenue.
A8: MODEL DESIGN. We forecast EBITDA margin and derive EBIT by subtracting a depreciation schedule built from capex vintages. Forecasting EBIT margin directly hides the depreciation assumption.
A10: KEY LIMITATION. The asset-life split driving the depreciation schedule is a stated assumption calibrated to reported D&A, not a disclosed figure. It is the most load-bearing assumption in the model.
A12: This is analytical research on public information. Not investment advice, not a recommendation to any person, and not a solicitation. Position sizing is illustrative against a notional $1bn book.
